sourcery_cli-1.20.0.data/purelib/sourcery/_asyncio.so
sourcery_cli-1.20.0.data/purelib/sourcery/_blake2.so
sourcery_cli-1.20.0.data/purelib/sourcery/_bz2.so
sourcery_cli-1.20.0.data/purelib/sourcery/_cffi_backend.so
sourcery_cli-1.20.0.data/purelib/sourcery/_codecs_cn.so
sourcery_cli-1.20.0.data/purelib/sourcery/_codecs_hk.so
sourcery_cli-1.20.0.data/purelib/sourcery/_codecs_iso2022.so
sourcery_cli-1.20.0.data/purelib/sourcery/_codecs_jp.so
sourcery_cli-1.20.0.data/purelib/sourcery/_codecs_kr.so
sourcery_cli-1.20.0.data/purelib/sourcery/_codecs_tw.so
sourcery_cli-1.20.0.data/purelib/sourcery/_contextvars.so
sourcery_cli-1.20.0.data/purelib/sourcery/_csv.so
sourcery_cli-1.20.0.data/purelib/sourcery/_ctypes.so
sourcery_cli-1.20.0.data/purelib/sourcery/_datetime.so
sourcery_cli-1.20.0.data/purelib/sourcery/_decimal.so
sourcery_cli-1.20.0.data/purelib/sourcery/_elementtree.so
sourcery_cli-1.20.0.data/purelib/sourcery/_hashlib.so
sourcery_cli-1.20.0.data/purelib/sourcery/_heapq.so
sourcery_cli-1.20.0.data/purelib/sourcery/_lzma.so
sourcery_cli-1.20.0.data/purelib/sourcery/_md5.so
sourcery_cli-1.20.0.data/purelib/sourcery/_multibytecodec.so
sourcery_cli-1.20.0.data/purelib/sourcery/_multiprocessing.so
sourcery_cli-1.20.0.data/purelib/sourcery/_opcode.so
sourcery_cli-1.20.0.data/purelib/sourcery/_pickle.so
sourcery_cli-1.20.0.data/purelib/sourcery/_posixshmem.so
sourcery_cli-1.20.0.data/purelib/sourcery/_posixsubprocess.so
sourcery_cli-1.20.0.data/purelib/sourcery/_queue.so
sourcery_cli-1.20.0.data/purelib/sourcery/_random.so
sourcery_cli-1.20.0.data/purelib/sourcery/_ruamel_yaml.so
sourcery_cli-1.20.0.data/purelib/sourcery/_scproxy.so
sourcery_cli-1.20.0.data/purelib/sourcery/_sha1.so
sourcery_cli-1.20.0.data/purelib/sourcery/_sha256.so
sourcery_cli-1.20.0.data/purelib/sourcery/_sha3.so
sourcery_cli-1.20.0.data/purelib/sourcery/_sha512.so
sourcery_cli-1.20.0.data/purelib/sourcery/_socket.so
sourcery_cli-1.20.0.data/purelib/sourcery/_sqlite3.so
sourcery_cli-1.20.0.dist-info/METADATA
sourcery_cli-1.20.0.dist-info/WHEEL
sourcery_cli-1.20.0.dist-info/entry_points.txt
sourcery_cli-1.20.0.dist-info/top_level.txt
sourcery_cli-1.20.0.dist-info/RECORD
