Metadata-Version: 2.1
Name: sourcery-cli
Version: 1.20.0
Summary: Magically refactor Python
Home-page: https://github.com/sourcery-ai/sourcery
Author: Sourcery AI
Author-email: hello@sourcery.ai
License: Proprietary
Classifier: Development Status :: 5 - Production/Stable
Classifier: Environment :: Console
Classifier: Environment :: Plugins
Classifier: Intended Audience :: Developers
Classifier: License :: Other/Proprietary License
Classifier: Operating System :: OS Independent
Classifier: Programming Language :: Python
Classifier: Topic :: Software Development :: Quality Assurance
Classifier: Topic :: Text Editors :: Integrated Development Environments (IDE)
